pratlib/__init__.py
pratlib/model_selection/__init__.py
pratlib/model_selection/train_test.py
pratlib/models/__init__.py
pratlib/models/classification/__init__.py
pratlib/models/classification/decision_tree.py
pratlib/models/classification/gradient_boosting.py
pratlib/models/classification/logistic_regression.py
pratlib/models/classification/naive_bayes.py
pratlib/models/classification/random_forest.py
pratlib/models/regression/__init__.py
pratlib/models/regression/decision_tree.py
pratlib/models/regression/gradient_boosting.py
pratlib/models/regression/linear_regression.py
pratlib/models/regression/random_forest.py
pratlib/preprocessing/__init__.py
pratlib/preprocessing/encoder.py
pratlib/preprocessing/imputer.py
pratlib/preprocessing/scaler.py
pratlib-1.1.4.dist-info/licenses/LICENSE
pratlib-1.1.4.dist-info/METADATA
pratlib-1.1.4.dist-info/WHEEL
pratlib-1.1.4.dist-info/top_level.txt
pratlib-1.1.4.dist-info/RECORD
