Metadata-Version: 2.4
Name: pratlib
Version: 1.1.4
Summary: A PySpark library for machine learning, similar to scikit-learn.
Home-page: https://github.com/pratiush1234/pratlib
Author: Pratiush
Author-email: pratiushanand1@gmail.com
Classifier: Programming Language :: Python :: 3
Classifier: License :: OSI Approved :: MIT License
Classifier: Operating System :: OS Independent
Requires-Python: >=3.6
License-File: LICENSE
Requires-Dist: pyspark>=3.0.0
Requires-Dist: asttokens==3.0.0
Requires-Dist: colorama==0.4.6
Requires-Dist: comm==0.2.2
Requires-Dist: debugpy==1.8.13
Requires-Dist: decorator==5.2.1
Requires-Dist: executing==2.2.0
Requires-Dist: ipykernel==6.29.5
Requires-Dist: ipython==9.0.2
Requires-Dist: ipython_pygments_lexers==1.1.1
Requires-Dist: jedi==0.19.2
Requires-Dist: jupyter_client==8.6.3
Requires-Dist: jupyter_core==5.7.2
Requires-Dist: matplotlib-inline==0.1.7
Requires-Dist: nest-asyncio==1.6.0
Requires-Dist: numpy==2.2.4
Requires-Dist: packaging==24.2
Requires-Dist: parso==0.8.4
Requires-Dist: platformdirs==4.3.7
Requires-Dist: prompt_toolkit==3.0.50
Requires-Dist: psutil==7.0.0
Requires-Dist: pure_eval==0.2.3
Requires-Dist: py4j==0.10.9.7
Requires-Dist: Pygments==2.19.1
Requires-Dist: pyspark==3.5.5
Requires-Dist: python-dateutil==2.9.0.post0
Requires-Dist: pywin32==310
Requires-Dist: pyzmq==26.3.0
Requires-Dist: six==1.17.0
Requires-Dist: stack-data==0.6.3
Requires-Dist: tornado==6.4.2
Requires-Dist: traitlets==5.14.3
Requires-Dist: wcwidth==0.2.13
Dynamic: author
Dynamic: author-email
Dynamic: classifier
Dynamic: description
Dynamic: description-content-type
Dynamic: home-page
Dynamic: license-file
Dynamic: requires-dist
Dynamic: requires-python
Dynamic: summary
